{
"type": "FeatureCollection",
"name": "Electric Substation",
"crs": { "type": "name", "properties": { "name": "urn:ogc:def:crs:OGC:1.3:CRS84" } },
"features": [
{ "type": "Feature", "properties": { "ID": 0 }, "geometry": { "type": "Point", "coordinates": [ 36.138958233307171, -0.303193152705534 ] } }
]
}
